pgfm.py
pgfm-0.7.3.dist-info/LICENSE
pgfm-0.7.3.dist-info/WHEEL
pgfm-0.7.3.dist-info/METADATA
pgfm-0.7.3.dist-info/RECORD
