Metadata-Version: 2.1
Name: pgfm
Version: 0.7.3
Summary: Python client for FileMaker Web APIs.
Keywords: FileMaker
Author-email: Mikhail Edoshin <mikhail.edoshin@mail.ru>
Requires-Python: >=3.8
Requires-Dist: lxml
Requires-Dist: requests
